ChomikBox/ChomikBox.py
ChomikBox/PartFile.py
ChomikBox/__init__.py
ChomikBox/__version__.py
ChomikBox/utils/FileTransferProgressBar.py
ChomikBox/utils/SeekableHTTPFile.py
ChomikBox/utils/__init__.py
pyChomikBox-0.2.0.dist-info/DESCRIPTION.rst
pyChomikBox-0.2.0.dist-info/METADATA
pyChomikBox-0.2.0.dist-info/RECORD
pyChomikBox-0.2.0.dist-info/WHEEL
pyChomikBox-0.2.0.dist-info/metadata.json
pyChomikBox-0.2.0.dist-info/top_level.txt
