Metadata-Version: 2.0
Name: pyChomikBox
Version: 0.2.0
Summary: Python library for Chomikuj.pl filesharing service
Home-page: https://github.com/JuniorJPDJ/pyChomikBox
Author: JuniorJPDJ
Author-email: juniorjpdj@interia.pl
License: LGPLv3+
Keywords: chomikuj chomik file share sharing upload download uploader downloader
Platform: UNKNOWN
Classifier: Development Status :: 3 - Alpha
Classifier: Topic :: Communications :: Chat
Classifier: License :: OSI Approved :: GNU Lesser General Public License v3 or later (LGPLv3+)
Classifier: Programming Language :: Python
Classifier: Programming Language :: Python :: 2.7
Classifier: Programming Language :: Python :: 3
Classifier: Programming Language :: Python :: 3.5
Classifier: Programming Language :: Python :: 3.6
Classifier: Programming Language :: Python :: Implementation :: CPython
Requires-Python: >=2.7, !=3.0.*, !=3.1.*, !=3.2.*, !=3.3.*, !=3.4.*, <4
Requires-Dist: requests
Requires-Dist: requests-toolbelt
Requires-Dist: xmltodict
